remoroo_core/__init__.py
remoroo_core/protocol.py
remoroo_core-0.1.1.dist-info/METADATA
remoroo_core-0.1.1.dist-info/WHEEL
remoroo_core-0.1.1.dist-info/top_level.txt
remoroo_core-0.1.1.dist-info/RECORD
