Metadata-Version: 2.4
Name: remoroo-core
Version: 0.1.1
Requires-Dist: pydantic>=2.0.0
Dynamic: requires-dist
